e2e/test_basic_example.py
e2e/apps/basic_example.py
streamlit_ketcher/__init__.py
streamlit_ketcher/frontend/asset-manifest.json
streamlit_ketcher/frontend/index.html
streamlit_ketcher/frontend/static/css/17.ec7f8f79.chunk.css
streamlit_ketcher/frontend/static/css/17.ec7f8f79.chunk.css.map
streamlit_ketcher/frontend/static/css/main.45d8a0de.css
streamlit_ketcher/frontend/static/css/main.45d8a0de.css.map
streamlit_ketcher/frontend/static/js/17.91376c0a.chunk.js
streamlit_ketcher/frontend/static/js/17.91376c0a.chunk.js.map
streamlit_ketcher/frontend/static/js/901.9b6ba14e.chunk.js
streamlit_ketcher/frontend/static/js/901.9b6ba14e.chunk.js.LICENSE.txt
streamlit_ketcher/frontend/static/js/901.9b6ba14e.chunk.js.map
streamlit_ketcher/frontend/static/js/main.869c7e58.js
streamlit_ketcher/frontend/static/js/main.869c7e58.js.LICENSE.txt
streamlit_ketcher/frontend/static/js/main.869c7e58.js.map
streamlit_ketcher/frontend/templates/library.svg
tests/__init__.py
tests/conftest.py
tests/test_streamlit_ketcher.py
streamlit_ketcher-0.0.1.dist-info/LICENSE
streamlit_ketcher-0.0.1.dist-info/METADATA
streamlit_ketcher-0.0.1.dist-info/NOTICES
streamlit_ketcher-0.0.1.dist-info/WHEEL
streamlit_ketcher-0.0.1.dist-info/top_level.txt
streamlit_ketcher-0.0.1.dist-info/RECORD
