Metadata-Version: 2.1
Name: streamlit-ketcher
Version: 0.0.1
Summary: Ketcher editor component for Streamlit.
Author-email: Kamil Bregula <dzakus13+pypi@gmail.com>
License: Apache-2.0
Project-URL: Homepage, https://github.com/mik-laj/streamlit-ketcher
Project-URL: Bug Tracker, https://github.com/mik-laj/streamlit-ketcher/issues
Project-URL: Demo, https://ketcher-editor.streamlit.app/
Classifier: Programming Language :: Python :: 3
Classifier: License :: OSI Approved :: Apache Software License
Classifier: Operating System :: OS Independent
Classifier: Intended Audience :: Science/Research
Classifier: Topic :: Scientific/Engineering :: Chemistry
Requires-Python: >=3.7
License-File: LICENSE
License-File: NOTICES
Requires-Dist: streamlit (>=1.0.0)
